{
    "exampleWaypoint": {
        "home": [94.14, -121.48, 101.14, -69.44, -90.36, 0]
    },
    "hopen": {
        "gripper": "open"
    },
    "hclose": {
        "gripper": "close"
    },
    "exampleSequence1": {
        "movement1": [-51.56, -75.14, 94.4, -19.07, -56.08, -0.92],
        "relative1(r)": [0, 0, -0.3, 0, 0, 0],
        "gripper": "close",
        "relative2(r)": [0, 0, 0.3, 0, 0, 0]
    },
    "exampleSequence2": {
        "movement2": [62.92, -60.45, 79.94, -20.37, -31.75, 0],
        "movement3": [62.04, -62.87, 83.68, -21.65, -32.63, -146, 4, 4],
        "relative3(r)": [0, 0.1, 0, 0, 0, 0, 3, 2],
        "relative4(r)": [0, -0.1, 0, 0, 0, 0, 3, 2],
        "rp movement2": "exampleSequence2"
    },
    "exampleSequence3": {
        "rp movement1": "getOil",
        "rp relative1(r)": "getOil",
        "gripper": "open",
        "rp relative2(r)": "getOil"
    }
}
